IPYNBrendertest/__init__.py
IPYNBrendertest/custom_exception.py
IPYNBrendertest/logger.py
IPYNBrendertest/site.py
IPYNBrendertest/youtube.py
pypi_project_hardik-0.0.3.dist-info/LICENSE
pypi_project_hardik-0.0.3.dist-info/METADATA
pypi_project_hardik-0.0.3.dist-info/WHEEL
pypi_project_hardik-0.0.3.dist-info/top_level.txt
pypi_project_hardik-0.0.3.dist-info/RECORD
